refgenDetector/__init__.py
refgenDetector/reference_genome_dictionaries.py
refgenDetector/refgenDetector_main.py
refgenDetector-1.0.1.dist-info/LICENSE
refgenDetector-1.0.1.dist-info/METADATA
refgenDetector-1.0.1.dist-info/WHEEL
refgenDetector-1.0.1.dist-info/entry_points.txt
refgenDetector-1.0.1.dist-info/top_level.txt
refgenDetector-1.0.1.dist-info/RECORD
