Metadata-Version: 2.1
Name: refgenDetector
Version: 1.0.1
Summary: refgenDetector
Home-page: UNKNOWN
Author: Mireia Marin Ginestar
Author-email: <mireia.marin@crg.eu>
License: UNKNOWN
Keywords: python
Platform: UNKNOWN
Classifier: Programming Language :: Python :: 3
Classifier: Operating System :: Unix
License-File: LICENSE
Requires-Dist: argparse
Requires-Dist: pysam
